Teknik-1.0.7.dist-info/DESCRIPTION.rst
Teknik-1.0.7.dist-info/METADATA
Teknik-1.0.7.dist-info/RECORD
Teknik-1.0.7.dist-info/WHEEL
Teknik-1.0.7.dist-info/metadata.json
Teknik-1.0.7.dist-info/top_level.txt
teknik/__init__.py
teknik/uploads.py
teknik/util.py
